spacey3d/__init__.py
spacey3d/cli.py
spacey3d/constants.py
spacey3d/upload.py
spacey3d/utils/__init__.py
spacey3d/utils/errors.py
spacey3d/utils/http.py
spacey3d-0.3.0.dist-info/licenses/LICENSE
spacey3d-0.3.0.dist-info/METADATA
spacey3d-0.3.0.dist-info/WHEEL
spacey3d-0.3.0.dist-info/entry_points.txt
spacey3d-0.3.0.dist-info/top_level.txt
spacey3d-0.3.0.dist-info/RECORD
