Metadata-Version: 2.4
Name: spacey3d
Version: 0.3.0
Summary: 3D Spacey SDK for Python - Upload and manage 3D models
Author-email: 3D Spacey Team <support@3dspacey.com>
Maintainer-email: 3D Spacey Team <support@3dspacey.com>
License-Expression: MIT
Project-URL: Homepage, https://github.com/3dspacey/spacey3d-python-sdk
Project-URL: Documentation, https://github.com/3dspacey/spacey3d-python-sdk#readme
Project-URL: Repository, https://github.com/3dspacey/spacey3d-python-sdk
Project-URL: Issues, https://github.com/3dspacey/spacey3d-python-sdk/issues
Keywords: 3d,models,upload,sdk,spacey,3dsmax,blender,cinema4d
Classifier: Development Status :: 4 - Beta
Classifier: Intended Audience :: Developers
Classifier: Operating System :: OS Independent
Classifier: Programming Language :: Python :: 3
Classifier: Programming Language :: Python :: 3.8
Classifier: Programming Language :: Python :: 3.9
Classifier: Programming Language :: Python :: 3.10
Classifier: Programming Language :: Python :: 3.11
Classifier: Programming Language :: Python :: 3.12
Classifier: Topic :: Software Development :: Libraries :: Python Modules
Classifier: Topic :: Multimedia :: Graphics :: 3D Modeling
Requires-Python: >=3.8
License-File: LICENSE
Requires-Dist: requests>=2.31.0
Provides-Extra: dev
Requires-Dist: pytest>=7.0; extra == "dev"
Requires-Dist: pytest-cov; extra == "dev"
Requires-Dist: black; extra == "dev"
Requires-Dist: flake8; extra == "dev"
Requires-Dist: mypy; extra == "dev"
Requires-Dist: twine; extra == "dev"
Requires-Dist: build; extra == "dev"
Dynamic: license-file
